[{"question": "Without the gray rubber sphere, what will happen?", "q_idx": 14, "obj_removed": [5, "grayrubbersphere"], "sim": {}, "sim_ASP_col": [{"frame": 39, "objects": [{"color": "red", "material": "rubber", "shape": "sphere"}, {"color": "green", "material": "rubber", "shape": "sphere"}]}, {"frame": 48, "objects": [{"color": "green", "material": "rubber", "shape": "sphere"}, {"color": "blue", "material": "metal", "shape": "sphere"}]}, {"frame": 158, "objects": [{"color": "red", "material": "rubber", "shape": "sphere"}, {"color": "gray", "material": "metal", "shape": "sphere"}]}], "too_early": false}]