{"objects": [{"color": "cyan", "material": "metal", "shape": "cylinder", "id": 0}, {"color": "cyan", "material": "metal", "shape": "sphere", "id": 1}, {"color": "brown", "material": "rubber", "shape": "cube", "id": 2}, {"color": "yellow", "material": "metal", "shape": "sphere", "id": 3}, {"color": "blue", "material": "rubber", "shape": "sphere", "id": 4}, {"color": "purple", "material": "rubber", "shape": "cube", "id": 5}], "predictions": [{"what_if": -1, "trajectory": [{"frame_index": 0, "objects": [{"x": 13.750012143434946, "y": 107.96877641817943, "color": "cyan", "material": "metal", "shape": "cylinder"}, {"x": 22.187542078044732, "y": 55.78118265307006, "color": "cyan", "material": "metal", "shape": "sphere"}, {"x": 37.49995133208122, "y": 115.15611874541493, "color": "yellow", "material": "metal", "shape": "sphere"}, {"x": 37.187526524040194, "y": 65.31240780619721, "color": "blue", "material": "rubber", "shape": "sphere"}, {"x": 57.49990498631498, "y": 129.06229935364547, "color": "purple", "material": "rubber", "shape": "cube"}]}, {"frame_index": 5, "objects": [{"x": 16.518130846005057, "y": 106.21535921306442, "color": "cyan", "material": "metal", "shape": "cylinder"}, {"x": 23.301204506718285, "y": 65.5169500337722, "color": "cyan", "material": "metal", "shape": "sphere"}, {"x": 37.500932439151725, "y": 115.1722831902089, "color": "yellow", "material": "metal", "shape": "sphere"}, {"x": 37.1584266300935, "y": 65.31878975408841, "color": "blue", "material": "rubber", "shape": "sphere"}, {"x": 57.50222735339521, "y": 129.0623116579616, "color": "purple", "material": "rubber", "shape": "cube"}]}, {"frame_index": 10, "objects": [{"x": 19.438843521723243, "y": 104.3652867734486, "color": "cyan", "material": "metal", "shape": "cylinder"}, {"x": 24.42435801075223, "y": 75.33566756481416, "color": "cyan", "material": "metal", "shape": "sphere"}, {"x": 74.78471236174634, "y": 0.4376613971497163, "color": "brown", "material": "rubber", "shape": "cube"}, {"x": 37.50191356963659, "y": 115.18844802077145, "color": "yellow", "material": "metal", "shape": "sphere"}, {"x": 37.129347405486165, "y": 65.32516716895115, "color": "blue", "material": "rubber", "shape": "sphere"}, {"x": 57.50222735339521, "y": 129.0623116579616, "color": "purple", "material": "rubber", "shape": "cube"}]}, {"frame_index": 15, "objects": [{"x": 22.523803596828053, "y": 102.41114882858788, "color": "cyan", "material": "metal", "shape": "cylinder"}, {"x": 25.557453063751833, "y": 85.24129421468584, "color": "cyan", "material": "metal", "shape": "sphere"}, {"x": 69.60299357562258, "y": 16.89578597314148, "color": "brown", "material": "rubber", "shape": "cube"}, {"x": 37.50289472353667, "y": 115.2046132371164, "color": "yellow", "material": "metal", "shape": "sphere"}, {"x": 37.10028882820421, "y": 65.3315400556134, "color": "blue", "material": "rubber", "shape": "sphere"}, {"x": 57.50222735339521, "y": 129.0623116579616, "color": "purple", "material": "rubber", "shape": "cube"}]}, {"frame_index": 20, "objects": [{"x": 25.247524914679502, "y": 103.30651733642217, "color": "cyan", "material": "metal", "shape": "cylinder"}, {"x": 27.357770755456613, "y": 91.62686737691708, "color": "cyan", "material": "metal", "shape": "sphere"}, {"x": 65.0230219493763, "y": 31.442631378755575, "color": "brown", "material": "rubber", "shape": "cube"}, {"x": 37.503875900852805, "y": 115.22077883925763, "color": "yellow", "material": "metal", "shape": "sphere"}, {"x": 37.0712683126707, "y": 65.33790635914987, "color": "blue", "material": "rubber", "shape": "sphere"}, {"x": 57.50222735339521, "y": 129.0623116579616, "color": "purple", "material": "rubber", "shape": "cube"}]}, {"frame_index": 25, "objects": [{"x": 26.952883369254454, "y": 110.21711311432516, "color": "cyan", "material": "metal", "shape": "cylinder"}, {"x": 30.64364696890911, "y": 90.67569041386975, "color": "cyan", "material": "metal", "shape": "sphere"}, {"x": 60.94798868993817, "y": 44.38566147333468, "color": "brown", "material": "rubber", "shape": "cube"}, {"x": 37.50485710158582, "y": 115.23694482720886, "color": "yellow", "material": "metal", "shape": "sphere"}, {"x": 37.04227075180324, "y": 65.34426786770393, "color": "blue", "material": "rubber", "shape": "sphere"}, {"x": 57.50222735339521, "y": 129.0623116579616, "color": "purple", "material": "rubber", "shape": "cube"}]}, {"frame_index": 30, "objects": [{"x": 28.67466954035037, "y": 117.19426361907989, "color": "cyan", "material": "metal", "shape": "cylinder"}, {"x": 34.174528798208854, "y": 89.65359171899671, "color": "cyan", "material": "metal", "shape": "sphere"}, {"x": 57.30096650792953, "y": 55.96925483330006, "color": "brown", "material": "rubber", "shape": "cube"}, {"x": 37.50583832573655, "y": 115.25311120098394, "color": "yellow", "material": "metal", "shape": "sphere"}, {"x": 37.013293744346505, "y": 65.35062486723395, "color": "blue", "material": "rubber", "shape": "sphere"}, {"x": 57.50222735339521, "y": 129.0623116579616, "color": "purple", "material": "rubber", "shape": "cube"}]}, {"frame_index": 35, "objects": [{"x": 30.411501783643654, "y": 124.23234582687269, "color": "cyan", "material": "metal", "shape": "cylinder"}, {"x": 37.97954421303421, "y": 88.55213811852664, "color": "cyan", "material": "metal", "shape": "sphere"}, {"x": 54.02005247721476, "y": 66.39005158507157, "color": "brown", "material": "rubber", "shape": "cube"}, {"x": 37.50681957330586, "y": 115.2692779605967, "color": "yellow", "material": "metal", "shape": "sphere"}, {"x": 36.98433726845597, "y": 65.35697736253223, "color": "blue", "material": "rubber", "shape": "sphere"}, {"x": 57.50222735339521, "y": 129.0623116579616, "color": "purple", "material": "rubber", "shape": "cube"}]}, {"frame_index": 40, "objects": [{"x": 32.161819038735736, "y": 131.32504355401412, "color": "cyan", "material": "metal", "shape": "cylinder"}, {"x": 42.09259410645752, "y": 87.36151985701298, "color": "cyan", "material": "metal", "shape": "sphere"}, {"x": 51.054861448540024, "y": 75.80806327918292, "color": "brown", "material": "rubber", "shape": "cube"}, {"x": 37.50780084429456, "y": 115.2854451060609, "color": "yellow", "material": "metal", "shape": "sphere"}, {"x": 36.95540169747807, "y": 65.36332531176117, "color": "blue", "material": "rubber", "shape": "sphere"}, {"x": 57.50222735339521, "y": 129.0623116579616, "color": "purple", "material": "rubber", "shape": "cube"}]}, {"frame_index": 45, "objects": [{"x": 33.92388718243056, "y": 138.46534334662672, "color": "cyan", "material": "metal", "shape": "cylinder"}, {"x": 42.695530414695725, "y": 91.91554934516073, "color": "cyan", "material": "metal", "shape": "sphere"}, {"x": 51.289605533265025, "y": 79.93208706059615, "color": "brown", "material": "rubber", "shape": "cube"}, {"x": 37.508782138703495, "y": 115.3016126373904, "color": "yellow", "material": "metal", "shape": "sphere"}, {"x": 36.92648621903011, "y": 65.36966881299287, "color": "blue", "material": "rubber", "shape": "sphere"}, {"x": 57.50222735339521, "y": 129.0623116579616, "color": "purple", "material": "rubber", "shape": "cube"}]}, {"frame_index": 50, "objects": [{"x": 35.69578392480166, "y": 145.64545425413053, "color": "cyan", "material": "metal", "shape": "cylinder"}, {"x": 41.47429113528389, "y": 99.1130941950507, "color": "cyan", "material": "metal", "shape": "sphere"}, {"x": 52.99069765185658, "y": 81.66582829238997, "color": "brown", "material": "rubber", "shape": "cube"}, {"x": 37.50976345653352, "y": 115.31778055459904, "color": "yellow", "material": "metal", "shape": "sphere"}, {"x": 36.89759120680035, "y": 65.37600782432897, "color": "blue", "material": "rubber", "shape": "sphere"}, {"x": 57.50222735339521, "y": 129.0623116579616, "color": "purple", "material": "rubber", "shape": "cube"}]}, {"frame_index": 55, "objects": [{"x": 37.47540049350507, "y": 152.85681710415113, "color": "cyan", "material": "metal", "shape": "cylinder"}, {"x": 40.34518964316406, "y": 105.87241646719751, "color": "cyan", "material": "metal", "shape": "sphere"}, {"x": 54.637021183138316, "y": 83.34374864882379, "color": "brown", "material": "rubber", "shape": "cube"}, {"x": 37.46617272481359, "y": 115.4845408958619, "color": "yellow", "material": "metal", "shape": "sphere"}, {"x": 36.868719004998255, "y": 65.38234207164413, "color": "blue", "material": "rubber", "shape": "sphere"}, {"x": 57.50222735339521, "y": 129.0623116579616, "color": "purple", "material": "rubber", "shape": "cube"}]}, {"frame_index": 60, "objects": [{"x": 40.14461625132382, "y": 109.42111603076046, "color": "cyan", "material": "metal", "shape": "sphere"}, {"x": 56.22125825793967, "y": 84.95839291531884, "color": "brown", "material": "rubber", "shape": "cube"}, {"x": 36.47208631415224, "y": 118.86227019335395, "color": "yellow", "material": "metal", "shape": "sphere"}, {"x": 36.83990426270933, "y": 65.38862354248022, "color": "blue", "material": "rubber", "shape": "sphere"}, {"x": 57.50222735339521, "y": 129.0623116579616, "color": "purple", "material": "rubber", "shape": "cube"}]}, {"frame_index": 65, "objects": [{"x": 39.94634187224433, "y": 112.92914501059322, "color": "cyan", "material": "metal", "shape": "sphere"}, {"x": 57.73603331637217, "y": 86.50224210962514, "color": "brown", "material": "rubber", "shape": "cube"}, {"x": 35.510146662080864, "y": 122.13076576724251, "color": "yellow", "material": "metal", "shape": "sphere"}, {"x": 36.81110986589573, "y": 65.39489874825796, "color": "blue", "material": "rubber", "shape": "sphere"}, {"x": 57.50222735339521, "y": 129.0623116579616, "color": "purple", "material": "rubber", "shape": "cube"}]}, {"frame_index": 70, "objects": [{"x": 39.750322754581006, "y": 116.39726737720845, "color": "cyan", "material": "metal", "shape": "sphere"}, {"x": 59.17396488164975, "y": 87.96776791858075, "color": "brown", "material": "rubber", "shape": "cube"}, {"x": 34.57878435119318, "y": 125.29537546324799, "color": "yellow", "material": "metal", "shape": "sphere"}, {"x": 36.78233579301687, "y": 65.40116952481033, "color": "blue", "material": "rubber", "shape": "sphere"}, {"x": 57.50222735339521, "y": 129.0623116579616, "color": "purple", "material": "rubber", "shape": "cube"}]}, {"frame_index": 75, "objects": [{"x": 39.55651593462093, "y": 119.82626919681624, "color": "cyan", "material": "metal", "shape": "sphere"}, {"x": 60.52774460990333, "y": 89.34752915139528, "color": "brown", "material": "rubber", "shape": "cube"}, {"x": 33.67652999397224, "y": 128.3610711937363, "color": "yellow", "material": "metal", "shape": "sphere"}, {"x": 36.753582022562505, "y": 65.4074358768251, "color": "blue", "material": "rubber", "shape": "sphere"}, {"x": 57.50222735339521, "y": 129.0623116579616, "color": "purple", "material": "rubber", "shape": "cube"}]}, {"frame_index": 80, "objects": [{"x": 39.36488005336097, "y": 123.21683639867896, "color": "cyan", "material": "metal", "shape": "sphere"}, {"x": 61.79023041034793, "y": 90.63424203857078, "color": "brown", "material": "rubber", "shape": "cube"}, {"x": 32.802008227664444, "y": 131.33253438464124, "color": "yellow", "material": "metal", "shape": "sphere"}, {"x": 36.72484853305273, "y": 65.41369780898343, "color": "blue", "material": "rubber", "shape": "sphere"}, {"x": 57.50222735339521, "y": 129.0623116579616, "color": "purple", "material": "rubber", "shape": "cube"}]}, {"frame_index": 85, "objects": [{"x": 39.1753740669479, "y": 126.5697061371138, "color": "cyan", "material": "metal", "shape": "sphere"}, {"x": 62.954523272707576, "y": 91.82087702844207, "color": "brown", "material": "rubber", "shape": "cube"}, {"x": 31.953931845972576, "y": 134.214162910026, "color": "yellow", "material": "metal", "shape": "sphere"}, {"x": 36.696135303037906, "y": 65.41995532595983, "color": "blue", "material": "rubber", "shape": "sphere"}, {"x": 57.50222735339521, "y": 129.0623116579616, "color": "purple", "material": "rubber", "shape": "cube"}]}, {"frame_index": 90, "objects": [{"x": 39.158929492944715, "y": 131.21018959043025, "color": "cyan", "material": "metal", "shape": "sphere"}, {"x": 62.86970726708846, "y": 79.30400265795635, "color": "brown", "material": "rubber", "shape": "cube"}, {"x": 32.31942620252005, "y": 133.7616303322029, "color": "yellow", "material": "metal", "shape": "sphere"}, {"x": 37.03126617305681, "y": 65.31242017777977, "color": "blue", "material": "rubber", "shape": "sphere"}, {"x": 57.49990746212995, "y": 129.06230066304022, "color": "purple", "material": "rubber", "shape": "cube"}]}, {"frame_index": 95, "objects": [{"x": 39.01038730893735, "y": 134.6016006577844, "color": "cyan", "material": "metal", "shape": "sphere"}, {"x": 63.705791664312635, "y": 79.49643207005778, "color": "brown", "material": "rubber", "shape": "cube"}, {"x": 31.494454568657027, "y": 136.08653330778782, "color": "yellow", "material": "metal", "shape": "sphere"}, {"x": 37.03124637833593, "y": 65.31242252342676, "color": "blue", "material": "rubber", "shape": "sphere"}, {"x": 57.49990746212995, "y": 129.06230066304022, "color": "purple", "material": "rubber", "shape": "cube"}]}, {"frame_index": 100, "objects": [{"x": 38.863349422491574, "y": 137.95865553394813, "color": "cyan", "material": "metal", "shape": "sphere"}, {"x": 64.41191355391504, "y": 79.65894874492157, "color": "brown", "material": "rubber", "shape": "cube"}, {"x": 30.69290725644303, "y": 138.34542105890762, "color": "yellow", "material": "metal", "shape": "sphere"}, {"x": 37.03122658362464, "y": 65.31242486907261, "color": "blue", "material": "rubber", "shape": "sphere"}, {"x": 57.49990746212995, "y": 129.06230066304022, "color": "purple", "material": "rubber", "shape": "cube"}]}, {"frame_index": 105, "objects": [{"x": 38.717790392265506, "y": 141.28194246334894, "color": "cyan", "material": "metal", "shape": "sphere"}, {"x": 64.98325321394086, "y": 79.79044419682222, "color": "brown", "material": "rubber", "shape": "cube"}, {"x": 29.913778173271133, "y": 140.5411084934522, "color": "yellow", "material": "metal", "shape": "sphere"}, {"x": 37.03120678892292, "y": 65.31242721471732, "color": "blue", "material": "rubber", "shape": "sphere"}, {"x": 57.49990746212995, "y": 129.06230066304022, "color": "purple", "material": "rubber", "shape": "cube"}]}, {"frame_index": 110, "objects": [{"x": 38.596782525837085, "y": 144.45910738179975, "color": "cyan", "material": "metal", "shape": "sphere"}, {"x": 65.31904180210357, "y": 79.84389281497468, "color": "brown", "material": "rubber", "shape": "cube"}, {"x": 29.924483734336942, "y": 142.56194113297, "color": "yellow", "material": "metal", "shape": "sphere"}, {"x": 37.03127409142835, "y": 65.32355639542338, "color": "blue", "material": "rubber", "shape": "sphere"}, {"x": 57.49990498631498, "y": 129.06229935364547, "color": "purple", "material": "rubber", "shape": "cube"}]}, {"frame_index": 115, "objects": [{"x": 38.604491363798275, "y": 147.77979038467, "color": "cyan", "material": "metal", "shape": "sphere"}, {"x": 65.6262555201634, "y": 79.8438461343476, "color": "brown", "material": "rubber", "shape": "cube"}, {"x": 29.736985190783635, "y": 144.6551132603572, "color": "yellow", "material": "metal", "shape": "sphere"}, {"x": 37.03127409262964, "y": 65.35139928518042, "color": "blue", "material": "rubber", "shape": "sphere"}, {"x": 57.49990498631498, "y": 129.06229935364547, "color": "purple", "material": "rubber", "shape": "cube"}]}, {"frame_index": 120, "objects": [{"x": 38.612152676336486, "y": 151.0801635560398, "color": "cyan", "material": "metal", "shape": "sphere"}, {"x": 65.78916649607993, "y": 79.84382143523548, "color": "brown", "material": "rubber", "shape": "cube"}, {"x": 29.551342454091607, "y": 146.72756631375884, "color": "yellow", "material": "metal", "shape": "sphere"}, {"x": 37.03127409383093, "y": 65.37924217493781, "color": "blue", "material": "rubber", "shape": "sphere"}, {"x": 57.49990498631498, "y": 129.06229935364547, "color": "purple", "material": "rubber", "shape": "cube"}]}, {"frame_index": 125, "objects": [{"x": 38.61976684827988, "y": 154.36048521154325, "color": "cyan", "material": "metal", "shape": "sphere"}, {"x": 65.81714918574079, "y": 79.84381714545505, "color": "brown", "material": "rubber", "shape": "cube"}, {"x": 29.367527020748703, "y": 148.77965664343998, "color": "yellow", "material": "metal", "shape": "sphere"}, {"x": 37.03127409503221, "y": 65.40708506469554, "color": "blue", "material": "rubber", "shape": "sphere"}, {"x": 57.49990498631498, "y": 129.06229935364547, "color": "purple", "material": "rubber", "shape": "cube"}]}], "collisions": [{"frame": 19, "objects": [{"color": "cyan", "material": "metal", "shape": "cylinder"}, {"color": "cyan", "material": "metal", "shape": "sphere"}]}, {"frame": 42, "objects": [{"color": "cyan", "material": "metal", "shape": "sphere"}, {"color": "brown", "material": "rubber", "shape": "cube"}]}, {"frame": 54, "objects": [{"color": "cyan", "material": "metal", "shape": "sphere"}, {"color": "yellow", "material": "metal", "shape": "sphere"}]}]}], "step_88": {"x": [[0.3028011918067932, 3.54719614982605], [-0.34697702527046204, 1.6978716850280762], [1.0134339332580566, 0.42860832810401917], [-0.9464945793151855, 2.1232080459594727], [-0.5228297114372253, -0.31244131922721863], [0.736231803894043, 1.4045584201812744]], "v": [[0.7008883953094482, 0.944246768951416], [-0.09392218291759491, 0.7614879012107849], [0.3148286044597626, 0.1544228345155716], [-0.4978499114513397, 0.8402754068374634], [-0.015246923081576824, 0.0006617846665903926], [0.0, 0.0]], "angle": [0.0, 0.0, 0.38746505975723267, 0.0, 0.0, 0.7599610686302185], "mass": [1.0398414134979248, 0.8925650715827942, 1.304389238357544, 0.7793677449226379, 1.0, 1.0], "restitution": [0.8513041138648987, 0.7086154222488403, 0.6831970810890198, 0.25921404361724854, 0.6000000238418579, 0.6000000238418579]}, "step_108": {"x": [[0.667525589466095, 4.038559436798096], [-0.3999530076980591, 2.1273820400238037], [1.1494410037994385, 0.4953191876411438], [-1.2263199090957642, 2.595499277114868], [-0.5315431356430054, -0.31206580996513367], [0.736231803894043, 1.4045584201812744]], "v": [[0.5771623253822327, 0.7775653004646301], [-0.09151449054479599, 0.7419672608375549], [0.16165883839130402, 0.07929307222366333], [-0.4817163050174713, 0.8130447268486023], [-0.015238913707435131, 0.0006614354206249118], [0.0, 0.0]], "angle": [0.0, 0.0, 0.38746505975723267, 0.0, 0.0, 0.7599610686302185], "mass": [1.0398414134979248, 0.8925650715827942, 1.304389238357544, 0.7793677449226379, 1.0, 1.0], "restitution": [0.8513041138648987, 0.7086154222488403, 0.6831970810890198, 0.25921404361724854, 0.6000000238418579, 0.6000000238418579]}}