{"objects": [{"color": "brown", "material": "rubber", "shape": "sphere", "id": 0}, {"color": "cyan", "material": "metal", "shape": "cube", "id": 1}, {"color": "purple", "material": "metal", "shape": "cylinder", "id": 2}, {"color": "yellow", "material": "metal", "shape": "cylinder", "id": 3}], "predictions": [{"what_if": -1, "trajectory": [{"frame_index": 0, "objects": [{"x": 25.625008057588648, "y": 75.78114000819902, "color": "purple", "material": "metal", "shape": "cylinder"}, {"x": 23.281260816887254, "y": 48.90618171882277, "color": "yellow", "material": "metal", "shape": "cylinder"}]}, {"frame_index": 5, "objects": [{"x": 25.625020955298798, "y": 75.78124208237189, "color": "purple", "material": "metal", "shape": "cylinder"}, {"x": 23.386147306684794, "y": 48.90666466995009, "color": "yellow", "material": "metal", "shape": "cylinder"}]}, {"frame_index": 10, "objects": [{"x": 25.625020955298798, "y": 75.78124208237189, "color": "purple", "material": "metal", "shape": "cylinder"}, {"x": 23.436369068730823, "y": 48.90689651945467, "color": "yellow", "material": "metal", "shape": "cylinder"}]}, {"frame_index": 15, "objects": [{"x": 25.625020955298798, "y": 75.78124208237189, "color": "purple", "material": "metal", "shape": "cylinder"}, {"x": 23.44110678559294, "y": 48.906918501084284, "color": "yellow", "material": "metal", "shape": "cylinder"}]}, {"frame_index": 20, "objects": [{"x": 74.11556575120468, "y": 155.57165242430864, "color": "brown", "material": "rubber", "shape": "sphere"}, {"x": 25.625020955298798, "y": 75.78124208237189, "color": "purple", "material": "metal", "shape": "cylinder"}, {"x": 23.44110678559294, "y": 48.906918501084284, "color": "yellow", "material": "metal", "shape": "cylinder"}]}, {"frame_index": 25, "objects": [{"x": 64.74766714268603, "y": 148.120882885124, "color": "brown", "material": "rubber", "shape": "sphere"}, {"x": 14.723541101842548, "y": 152.55531136100876, "color": "cyan", "material": "metal", "shape": "cube"}, {"x": 25.625020955298798, "y": 75.78124208237189, "color": "purple", "material": "metal", "shape": "cylinder"}, {"x": 23.44110678559294, "y": 48.906918501084284, "color": "yellow", "material": "metal", "shape": "cylinder"}]}, {"frame_index": 30, "objects": [{"x": 56.90728657754982, "y": 141.88503925360595, "color": "brown", "material": "rubber", "shape": "sphere"}, {"x": 16.135448495993014, "y": 147.7958600441532, "color": "cyan", "material": "metal", "shape": "cube"}, {"x": 25.625020955298798, "y": 75.78124208237189, "color": "purple", "material": "metal", "shape": "cylinder"}, {"x": 23.44110678559294, "y": 48.906918501084284, "color": "yellow", "material": "metal", "shape": "cylinder"}]}, {"frame_index": 35, "objects": [{"x": 50.24755573392181, "y": 136.58822486905223, "color": "brown", "material": "rubber", "shape": "sphere"}, {"x": 17.559413789231648, "y": 142.99572020855044, "color": "cyan", "material": "metal", "shape": "cube"}, {"x": 25.625020955298798, "y": 75.78124208237189, "color": "purple", "material": "metal", "shape": "cylinder"}, {"x": 23.44110678559294, "y": 48.906918501084284, "color": "yellow", "material": "metal", "shape": "cylinder"}]}, {"frame_index": 40, "objects": [{"x": 44.519305022755326, "y": 132.0322673742997, "color": "brown", "material": "rubber", "shape": "sphere"}, {"x": 18.994686531161015, "y": 138.1575146930239, "color": "cyan", "material": "metal", "shape": "cube"}, {"x": 25.625020955298798, "y": 75.78124208237189, "color": "purple", "material": "metal", "shape": "cylinder"}, {"x": 23.44110678559294, "y": 48.906918501084284, "color": "yellow", "material": "metal", "shape": "cylinder"}]}, {"frame_index": 45, "objects": [{"x": 39.53890528633193, "y": 128.07110945882468, "color": "brown", "material": "rubber", "shape": "sphere"}, {"x": 20.440385011007322, "y": 133.28412726030757, "color": "cyan", "material": "metal", "shape": "cube"}, {"x": 25.625020955298798, "y": 75.78124208237189, "color": "purple", "material": "metal", "shape": "cylinder"}, {"x": 23.44110678559294, "y": 48.906918501084284, "color": "yellow", "material": "metal", "shape": "cylinder"}]}, {"frame_index": 50, "objects": [{"x": 35.16805261621879, "y": 124.59475029616866, "color": "brown", "material": "rubber", "shape": "sphere"}, {"x": 21.895546140976364, "y": 128.37889181794364, "color": "cyan", "material": "metal", "shape": "cube"}, {"x": 25.625020955298798, "y": 75.78124208237189, "color": "purple", "material": "metal", "shape": "cylinder"}, {"x": 23.44110678559294, "y": 48.906918501084284, "color": "yellow", "material": "metal", "shape": "cylinder"}]}, {"frame_index": 55, "objects": [{"x": 31.300591633460012, "y": 121.51876361292724, "color": "brown", "material": "rubber", "shape": "sphere"}, {"x": 23.35908100776907, "y": 123.44540149717541, "color": "cyan", "material": "metal", "shape": "cube"}, {"x": 25.625020955298798, "y": 75.78124208237189, "color": "purple", "material": "metal", "shape": "cylinder"}, {"x": 23.44110678559294, "y": 48.906918501084284, "color": "yellow", "material": "metal", "shape": "cylinder"}]}, {"frame_index": 60, "objects": [{"x": 28.807647637798503, "y": 118.25931622594652, "color": "brown", "material": "rubber", "shape": "sphere"}, {"x": 23.83910851913014, "y": 119.05150322076523, "color": "cyan", "material": "metal", "shape": "cube"}, {"x": 25.625020955298798, "y": 75.78124208237189, "color": "purple", "material": "metal", "shape": "cylinder"}, {"x": 23.44110678559294, "y": 48.906918501084284, "color": "yellow", "material": "metal", "shape": "cylinder"}]}, {"frame_index": 65, "objects": [{"x": 28.43978894261534, "y": 114.07393807359885, "color": "brown", "material": "rubber", "shape": "sphere"}, {"x": 22.34284473215374, "y": 116.00969820935899, "color": "cyan", "material": "metal", "shape": "cube"}, {"x": 25.625020955298798, "y": 75.78124208237189, "color": "purple", "material": "metal", "shape": "cylinder"}, {"x": 23.44110678559294, "y": 48.906918501084284, "color": "yellow", "material": "metal", "shape": "cylinder"}]}, {"frame_index": 70, "objects": [{"x": 28.078770786830372, "y": 109.96655900405274, "color": "brown", "material": "rubber", "shape": "sphere"}, {"x": 20.971237332575082, "y": 113.22131940518432, "color": "cyan", "material": "metal", "shape": "cube"}, {"x": 25.625020955298798, "y": 75.78124208237189, "color": "purple", "material": "metal", "shape": "cylinder"}, {"x": 23.44110678559294, "y": 48.906918501084284, "color": "yellow", "material": "metal", "shape": "cylinder"}]}, {"frame_index": 75, "objects": [{"x": 27.724406794989243, "y": 105.93486357412847, "color": "brown", "material": "rubber", "shape": "sphere"}, {"x": 19.7118292300393, "y": 110.66104759931997, "color": "cyan", "material": "metal", "shape": "cube"}, {"x": 25.625020955298798, "y": 75.78124208237189, "color": "purple", "material": "metal", "shape": "cylinder"}, {"x": 23.44110678559294, "y": 48.906918501084284, "color": "yellow", "material": "metal", "shape": "cylinder"}]}, {"frame_index": 80, "objects": [{"x": 27.376512987001657, "y": 101.97663230979813, "color": "brown", "material": "rubber", "shape": "sphere"}, {"x": 18.553883062524896, "y": 108.30703591135794, "color": "cyan", "material": "metal", "shape": "cube"}, {"x": 25.625020955298798, "y": 75.78124208237189, "color": "purple", "material": "metal", "shape": "cylinder"}, {"x": 23.44110678559294, "y": 48.906918501084284, "color": "yellow", "material": "metal", "shape": "cylinder"}]}, {"frame_index": 85, "objects": [{"x": 27.034880855455654, "y": 98.08971592274327, "color": "brown", "material": "rubber", "shape": "sphere"}, {"x": 17.488110571493415, "y": 106.14040629439597, "color": "cyan", "material": "metal", "shape": "cube"}, {"x": 25.625020955298798, "y": 75.78124208237189, "color": "purple", "material": "metal", "shape": "cylinder"}, {"x": 23.44110678559294, "y": 48.906918501084284, "color": "yellow", "material": "metal", "shape": "cylinder"}]}, {"frame_index": 90, "objects": [{"x": 25.62423218539294, "y": 83.82142205731961, "color": "brown", "material": "rubber", "shape": "sphere"}, {"x": 17.76916465016577, "y": 115.20301226785116, "color": "cyan", "material": "metal", "shape": "cube"}, {"x": 25.42552597732078, "y": 72.9563308445124, "color": "purple", "material": "metal", "shape": "cylinder"}, {"x": 23.391700274486332, "y": 48.90788195764565, "color": "yellow", "material": "metal", "shape": "cylinder"}]}, {"frame_index": 95, "objects": [{"x": 25.24876404313423, "y": 81.09702913209804, "color": "brown", "material": "rubber", "shape": "sphere"}, {"x": 16.932601433507187, "y": 114.57799230539091, "color": "cyan", "material": "metal", "shape": "cube"}, {"x": 25.259689048050905, "y": 68.44465001465268, "color": "purple", "material": "metal", "shape": "cylinder"}, {"x": 23.315826582264204, "y": 48.91053031287098, "color": "yellow", "material": "metal", "shape": "cylinder"}]}, {"frame_index": 100, "objects": [{"x": 24.879675807579304, "y": 78.41892903162825, "color": "brown", "material": "rubber", "shape": "sphere"}, {"x": 16.16728608048375, "y": 114.00620395680677, "color": "cyan", "material": "metal", "shape": "cube"}, {"x": 25.102004624008746, "y": 64.15471099468895, "color": "purple", "material": "metal", "shape": "cylinder"}, {"x": 23.294501522388426, "y": 48.91125219962625, "color": "yellow", "material": "metal", "shape": "cylinder"}]}, {"frame_index": 105, "objects": [{"x": 24.516797366381308, "y": 75.78589688006855, "color": "brown", "material": "rubber", "shape": "sphere"}, {"x": 15.468180472324866, "y": 113.48388095937135, "color": "cyan", "material": "metal", "shape": "cube"}, {"x": 24.952222957852648, "y": 60.0797560214005, "color": "purple", "material": "metal", "shape": "cylinder"}, {"x": 23.294501522388426, "y": 48.91125219962625, "color": "yellow", "material": "metal", "shape": "cylinder"}]}, {"frame_index": 110, "objects": [{"x": 24.239671260666874, "y": 73.02663315359268, "color": "brown", "material": "rubber", "shape": "sphere"}, {"x": 14.784290338208427, "y": 112.77594506876144, "color": "cyan", "material": "metal", "shape": "cube"}, {"x": 24.90624068726507, "y": 57.3515649509344, "color": "purple", "material": "metal", "shape": "cylinder"}, {"x": 23.17350851166249, "y": 48.166379814210714, "color": "yellow", "material": "metal", "shape": "cylinder"}]}, {"frame_index": 115, "objects": [{"x": 23.905217279846344, "y": 70.46568241433239, "color": "brown", "material": "rubber", "shape": "sphere"}, {"x": 14.282278908658725, "y": 112.32705097010803, "color": "cyan", "material": "metal", "shape": "cube"}, {"x": 25.053550553333103, "y": 55.52768550530435, "color": "purple", "material": "metal", "shape": "cylinder"}, {"x": 22.922859498570126, "y": 46.80878282995729, "color": "yellow", "material": "metal", "shape": "cylinder"}]}, {"frame_index": 120, "objects": [{"x": 23.57606839658022, "y": 67.94535281618185, "color": "brown", "material": "rubber", "shape": "sphere"}, {"x": 13.831362525657655, "y": 111.9238401355174, "color": "cyan", "material": "metal", "shape": "cube"}, {"x": 25.188148144730754, "y": 53.861194094207335, "color": "purple", "material": "metal", "shape": "cylinder"}, {"x": 22.698388696943656, "y": 45.59291525745325, "color": "yellow", "material": "metal", "shape": "cylinder"}]}, {"frame_index": 125, "objects": [{"x": 23.25209138856661, "y": 65.46463573121986, "color": "brown", "material": "rubber", "shape": "sphere"}, {"x": 13.429057748581778, "y": 111.56409864412716, "color": "cyan", "material": "metal", "shape": "cube"}, {"x": 25.309984873564638, "y": 52.352686777801566, "color": "purple", "material": "metal", "shape": "cylinder"}, {"x": 22.49940326140991, "y": 44.515165987105405, "color": "yellow", "material": "metal", "shape": "cylinder"}]}], "collisions": [{"frame": 59, "objects": [{"color": "brown", "material": "rubber", "shape": "sphere"}, {"color": "cyan", "material": "metal", "shape": "cube"}]}, {"frame": 86, "objects": [{"color": "brown", "material": "rubber", "shape": "sphere"}, {"color": "purple", "material": "metal", "shape": "cylinder"}]}, {"frame": 109, "objects": [{"color": "purple", "material": "metal", "shape": "cylinder"}, {"color": "yellow", "material": "metal", "shape": "cylinder"}]}]}], "step_88": {"x": [[-1.3733336925506592, 0.7716763019561768], [-2.5081207752227783, 1.2898828983306885], [-1.4940587282180786, 0.029493847861886024], [-1.7232098579406738, -1.016661524772644]], "v": [[-0.23038876056671143, -0.964786946773529], [-0.9031214118003845, -0.45444485545158386], [0.0, 0.0], [0.0, 0.0]], "angle": [0.0, 1.0904847383499146, 0.0, 0.0], "mass": [1.6514240503311157, 1.4157356023788452, -0.18033142387866974, 1.0321736335754395], "restitution": [0.5837321281433105, 0.49483996629714966, 0.6902278661727905, 0.5808625817298889]}, "step_108": {"x": [[-1.5060590505599976, 0.19524896144866943], [-2.9734532833099365, 1.055729866027832], [-1.5237040519714355, -0.2791738510131836], [-1.7232098579406738, -1.016661524772644]], "v": [[-0.237941175699234, -1.0934406518936157], [-0.7273746728897095, -0.3660130202770233], [-0.13624100387096405, -1.418544888496399], [0.0, 0.0]], "angle": [0.0, 1.0904847383499146, 0.0, 0.0], "mass": [1.6514240503311157, 1.4157356023788452, -0.18033142387866974, 1.0321736335754395], "restitution": [0.5837321281433105, 0.49483996629714966, 0.6902278661727905, 0.5808625817298889]}}