{"objects": [{"color": "gray", "material": "metal", "shape": "cylinder", "id": 0}, {"color": "green", "material": "rubber", "shape": "sphere", "id": 1}, {"color": "cyan", "material": "metal", "shape": "cube", "id": 2}, {"color": "red", "material": "rubber", "shape": "cylinder", "id": 3}, {"color": "blue", "material": "rubber", "shape": "sphere", "id": 4}, {"color": "yellow", "material": "rubber", "shape": "sphere", "id": 5}], "predictions": [{"what_if": -1, "trajectory": [{"frame_index": 0, "objects": [{"x": 31.562546795789334, "y": 92.50007083248197, "color": "green", "material": "rubber", "shape": "sphere"}, {"x": 37.031276248219555, "y": 115.31261975551001, "color": "blue", "material": "rubber", "shape": "sphere"}, {"x": 30.000005053694036, "y": 35.000045787259836, "color": "yellow", "material": "rubber", "shape": "sphere"}]}, {"frame_index": 5, "objects": [{"x": 31.562546795789334, "y": 92.50007083248197, "color": "green", "material": "rubber", "shape": "sphere"}, {"x": 37.031276248219555, "y": 115.31261975551001, "color": "blue", "material": "rubber", "shape": "sphere"}, {"x": 30.000005053694036, "y": 35.000045787259836, "color": "yellow", "material": "rubber", "shape": "sphere"}]}, {"frame_index": 10, "objects": [{"x": 31.562546795789334, "y": 92.50007083248197, "color": "green", "material": "rubber", "shape": "sphere"}, {"x": 37.031276248219555, "y": 115.31261975551001, "color": "blue", "material": "rubber", "shape": "sphere"}, {"x": 30.000005053694036, "y": 35.000045787259836, "color": "yellow", "material": "rubber", "shape": "sphere"}]}, {"frame_index": 15, "objects": [{"x": 31.562546795789334, "y": 92.50007083248197, "color": "green", "material": "rubber", "shape": "sphere"}, {"x": -2.3922689365817447, "y": 129.96657152890867, "color": "cyan", "material": "metal", "shape": "cube"}, {"x": 37.031276248219555, "y": 115.31261975551001, "color": "blue", "material": "rubber", "shape": "sphere"}, {"x": 30.000005053694036, "y": 35.000045787259836, "color": "yellow", "material": "rubber", "shape": "sphere"}]}, {"frame_index": 20, "objects": [{"x": 101.23552595591721, "y": 139.96764496326315, "color": "gray", "material": "metal", "shape": "cylinder"}, {"x": 31.562546795789334, "y": 92.50007083248197, "color": "green", "material": "rubber", "shape": "sphere"}, {"x": -1.2840687492277565, "y": 128.2908295243127, "color": "cyan", "material": "metal", "shape": "cube"}, {"x": 37.031276248219555, "y": 115.31261975551001, "color": "blue", "material": "rubber", "shape": "sphere"}, {"x": 30.000005053694036, "y": 35.000045787259836, "color": "yellow", "material": "rubber", "shape": "sphere"}]}, {"frame_index": 25, "objects": [{"x": 88.3656550067618, "y": 132.00077302307355, "color": "gray", "material": "metal", "shape": "cylinder"}, {"x": 31.562546795789334, "y": 92.50007083248197, "color": "green", "material": "rubber", "shape": "sphere"}, {"x": -0.1611611957268394, "y": 126.59288465996191, "color": "cyan", "material": "metal", "shape": "cube"}, {"x": 37.031276248219555, "y": 115.31261975551001, "color": "blue", "material": "rubber", "shape": "sphere"}, {"x": 30.000005053694036, "y": 35.000045787259836, "color": "yellow", "material": "rubber", "shape": "sphere"}]}, {"frame_index": 30, "objects": [{"x": 77.95224667331877, "y": 125.55451016791767, "color": "gray", "material": "metal", "shape": "cylinder"}, {"x": 31.562546795789334, "y": 92.50007083248197, "color": "green", "material": "rubber", "shape": "sphere"}, {"x": 0.9760515060536741, "y": 124.87329587782129, "color": "cyan", "material": "metal", "shape": "cube"}, {"x": 37.031276248219555, "y": 115.31261975551001, "color": "blue", "material": "rubber", "shape": "sphere"}, {"x": 30.000005053694036, "y": 35.000045787259836, "color": "yellow", "material": "rubber", "shape": "sphere"}]}, {"frame_index": 35, "objects": [{"x": 69.35869520493635, "y": 120.23482261458464, "color": "gray", "material": "metal", "shape": "cylinder"}, {"x": 31.562546795789334, "y": 92.50007083248197, "color": "green", "material": "rubber", "shape": "sphere"}, {"x": 2.1270845345876186, "y": 123.13281367209669, "color": "cyan", "material": "metal", "shape": "cube"}, {"x": 37.031276248219555, "y": 115.31261975551001, "color": "blue", "material": "rubber", "shape": "sphere"}, {"x": 30.000005053694036, "y": 35.000045787259836, "color": "yellow", "material": "rubber", "shape": "sphere"}]}, {"frame_index": 40, "objects": [{"x": 62.15116419148545, "y": 115.77311171331091, "color": "gray", "material": "metal", "shape": "cylinder"}, {"x": 31.562546795789334, "y": 92.50007083248197, "color": "green", "material": "rubber", "shape": "sphere"}, {"x": 3.291362846554674, "y": 121.37229382966969, "color": "cyan", "material": "metal", "shape": "cube"}, {"x": -3.0874921877236106, "y": 75.5586862066273, "color": "red", "material": "rubber", "shape": "cylinder"}, {"x": 37.031276248219555, "y": 115.31261975551001, "color": "blue", "material": "rubber", "shape": "sphere"}, {"x": 30.000005053694036, "y": 35.000045787259836, "color": "yellow", "material": "rubber", "shape": "sphere"}]}, {"frame_index": 45, "objects": [{"x": 56.0239094261676, "y": 111.98013567747496, "color": "gray", "material": "metal", "shape": "cylinder"}, {"x": 31.562546795789334, "y": 92.50007083248197, "color": "green", "material": "rubber", "shape": "sphere"}, {"x": 4.468218846940658, "y": 119.59274904064199, "color": "cyan", "material": "metal", "shape": "cube"}, {"x": -2.021666631373618, "y": 75.69860045766445, "color": "red", "material": "rubber", "shape": "cylinder"}, {"x": 37.031276248219555, "y": 115.31261975551001, "color": "blue", "material": "rubber", "shape": "sphere"}, {"x": 30.000005053694036, "y": 35.000045787259836, "color": "yellow", "material": "rubber", "shape": "sphere"}]}, {"frame_index": 50, "objects": [{"x": 50.75519261449774, "y": 108.71864700900443, "color": "gray", "material": "metal", "shape": "cylinder"}, {"x": 31.562546795789334, "y": 92.50007083248197, "color": "green", "material": "rubber", "shape": "sphere"}, {"x": 5.656880361425306, "y": 117.79537610287606, "color": "cyan", "material": "metal", "shape": "cube"}, {"x": -0.9427928947106632, "y": 75.84022773877612, "color": "red", "material": "rubber", "shape": "cylinder"}, {"x": 37.031276248219555, "y": 115.31261975551001, "color": "blue", "material": "rubber", "shape": "sphere"}, {"x": 30.000005053694036, "y": 35.000045787259836, "color": "yellow", "material": "rubber", "shape": "sphere"}]}, {"frame_index": 55, "objects": [{"x": 46.18032711965158, "y": 105.88667475632758, "color": "gray", "material": "metal", "shape": "cylinder"}, {"x": 31.562546795789334, "y": 92.50007083248197, "color": "green", "material": "rubber", "shape": "sphere"}, {"x": 6.856452886735924, "y": 115.98147932419813, "color": "cyan", "material": "metal", "shape": "cube"}, {"x": 0.14844613645611723, "y": 75.98347722184835, "color": "red", "material": "rubber", "shape": "cylinder"}, {"x": 37.031276248219555, "y": 115.31261975551001, "color": "blue", "material": "rubber", "shape": "sphere"}, {"x": 30.000005053694036, "y": 35.000045787259836, "color": "yellow", "material": "rubber", "shape": "sphere"}]}, {"frame_index": 60, "objects": [{"x": 42.17442691648587, "y": 103.40690935082894, "color": "gray", "material": "metal", "shape": "cylinder"}, {"x": 31.562546795789334, "y": 92.50007083248197, "color": "green", "material": "rubber", "shape": "sphere"}, {"x": 8.065956609783807, "y": 114.15259002992023, "color": "cyan", "material": "metal", "shape": "cube"}, {"x": 1.2512405876626413, "y": 76.12824460859682, "color": "red", "material": "rubber", "shape": "cylinder"}, {"x": 37.031276248219555, "y": 115.31261975551001, "color": "blue", "material": "rubber", "shape": "sphere"}, {"x": 30.000005053694036, "y": 35.000045787259836, "color": "yellow", "material": "rubber", "shape": "sphere"}]}, {"frame_index": 65, "objects": [{"x": 38.64108158994986, "y": 101.21967043925099, "color": "gray", "material": "metal", "shape": "cylinder"}, {"x": 31.562546795789334, "y": 92.50007083248197, "color": "green", "material": "rubber", "shape": "sphere"}, {"x": 9.284272261658657, "y": 112.31039184344728, "color": "cyan", "material": "metal", "shape": "cube"}, {"x": 2.3646871501708158, "y": 76.27440965586675, "color": "red", "material": "rubber", "shape": "cylinder"}, {"x": 37.031276248219555, "y": 115.31261975551001, "color": "blue", "material": "rubber", "shape": "sphere"}, {"x": 30.000005053694036, "y": 35.000045787259836, "color": "yellow", "material": "rubber", "shape": "sphere"}]}, {"frame_index": 70, "objects": [{"x": 35.58320198196084, "y": 99.4073109716338, "color": "gray", "material": "metal", "shape": "cylinder"}, {"x": 31.411824258046746, "y": 92.25246582330485, "color": "green", "material": "rubber", "shape": "sphere"}, {"x": 10.510153067077052, "y": 110.45675162197102, "color": "cyan", "material": "metal", "shape": "cube"}, {"x": 3.4877613683425825, "y": 76.42183860665996, "color": "red", "material": "rubber", "shape": "cylinder"}, {"x": 37.031276248219555, "y": 115.31261975551001, "color": "blue", "material": "rubber", "shape": "sphere"}, {"x": 30.000005053694036, "y": 35.000045787259836, "color": "yellow", "material": "rubber", "shape": "sphere"}]}, {"frame_index": 75, "objects": [{"x": 33.49242014582286, "y": 98.86034028988662, "color": "gray", "material": "metal", "shape": "cylinder"}, {"x": 29.973501928707343, "y": 89.8895805722482, "color": "green", "material": "rubber", "shape": "sphere"}, {"x": 11.742243588435523, "y": 108.59372706643192, "color": "cyan", "material": "metal", "shape": "cube"}, {"x": 4.619302423683746, "y": 76.57037937457713, "color": "red", "material": "rubber", "shape": "cylinder"}, {"x": 37.031276248219555, "y": 115.31261975551001, "color": "blue", "material": "rubber", "shape": "sphere"}, {"x": 30.000005053694036, "y": 35.000045787259836, "color": "yellow", "material": "rubber", "shape": "sphere"}]}, {"frame_index": 80, "objects": [{"x": 31.595768580111514, "y": 98.36415840963463, "color": "gray", "material": "metal", "shape": "cylinder"}, {"x": 28.600358520408786, "y": 87.63377230293213, "color": "green", "material": "rubber", "shape": "sphere"}, {"x": 12.979044809997108, "y": 106.72358800972599, "color": "cyan", "material": "metal", "shape": "cube"}, {"x": 5.758049747666086, "y": 76.719865306812, "color": "red", "material": "rubber", "shape": "cylinder"}, {"x": 37.031276248219555, "y": 115.31261975551001, "color": "blue", "material": "rubber", "shape": "sphere"}, {"x": 30.000005053694036, "y": 35.000045787259836, "color": "yellow", "material": "rubber", "shape": "sphere"}]}, {"frame_index": 85, "objects": [{"x": 29.87141891664411, "y": 97.91305361756234, "color": "gray", "material": "metal", "shape": "cylinder"}, {"x": 27.288012498440633, "y": 85.47784581819226, "color": "green", "material": "rubber", "shape": "sphere"}, {"x": 14.21892447792426, "y": 104.84877594138486, "color": "cyan", "material": "metal", "shape": "cube"}, {"x": 6.902589457031678, "y": 76.87011138569629, "color": "red", "material": "rubber", "shape": "cylinder"}, {"x": 37.031276248219555, "y": 115.31261975551001, "color": "blue", "material": "rubber", "shape": "sphere"}, {"x": 30.000005053694036, "y": 35.000045787259836, "color": "yellow", "material": "rubber", "shape": "sphere"}]}, {"frame_index": 90, "objects": [{"x": 29.32579521987588, "y": 93.50427133217335, "color": "gray", "material": "metal", "shape": "cylinder"}, {"x": 25.113289673546046, "y": 86.09146312941643, "color": "green", "material": "rubber", "shape": "sphere"}, {"x": 15.360760634863935, "y": 102.25216287214033, "color": "cyan", "material": "metal", "shape": "cube"}, {"x": 7.8314024642506315, "y": 77.0998391129326, "color": "red", "material": "rubber", "shape": "cylinder"}, {"x": 37.031276248219555, "y": 115.31261975551001, "color": "blue", "material": "rubber", "shape": "sphere"}, {"x": 30.000005053694036, "y": 35.000045787259836, "color": "yellow", "material": "rubber", "shape": "sphere"}]}, {"frame_index": 95, "objects": [{"x": 28.111867661301908, "y": 92.92855857369993, "color": "gray", "material": "metal", "shape": "cylinder"}, {"x": 23.872935873164764, "y": 84.94981225914003, "color": "green", "material": "rubber", "shape": "sphere"}, {"x": 16.654545751729852, "y": 100.4588684319314, "color": "cyan", "material": "metal", "shape": "cube"}, {"x": 9.055578358714255, "y": 77.27210278875963, "color": "red", "material": "rubber", "shape": "cylinder"}, {"x": 37.031276248219555, "y": 115.31261975551001, "color": "blue", "material": "rubber", "shape": "sphere"}, {"x": 30.000005053694036, "y": 35.000045787259836, "color": "yellow", "material": "rubber", "shape": "sphere"}]}, {"frame_index": 100, "objects": [{"x": 27.005643321689618, "y": 92.40392242174799, "color": "gray", "material": "metal", "shape": "cylinder"}, {"x": 22.685343968676797, "y": 83.85673363780954, "color": "green", "material": "rubber", "shape": "sphere"}, {"x": 17.948519435304984, "y": 98.66531452108376, "color": "cyan", "material": "metal", "shape": "cube"}, {"x": 10.285526079750433, "y": 77.44517846284974, "color": "red", "material": "rubber", "shape": "cylinder"}, {"x": 37.031276248219555, "y": 115.31261975551001, "color": "blue", "material": "rubber", "shape": "sphere"}, {"x": 30.000005053694036, "y": 35.000045787259836, "color": "yellow", "material": "rubber", "shape": "sphere"}]}, {"frame_index": 105, "objects": [{"x": 25.998295750402058, "y": 91.9261817073446, "color": "gray", "material": "metal", "shape": "cylinder"}, {"x": 21.547191309838265, "y": 82.80915600839117, "color": "green", "material": "rubber", "shape": "sphere"}, {"x": 19.24048353727975, "y": 96.87453181633317, "color": "cyan", "material": "metal", "shape": "cube"}, {"x": 11.519404581339256, "y": 77.61880827113403, "color": "red", "material": "rubber", "shape": "cylinder"}, {"x": 37.031276248219555, "y": 115.31261975551001, "color": "blue", "material": "rubber", "shape": "sphere"}, {"x": 30.000005053694036, "y": 35.000045787259836, "color": "yellow", "material": "rubber", "shape": "sphere"}]}, {"frame_index": 110, "objects": [{"x": 25.018192983970206, "y": 91.46796415003098, "color": "gray", "material": "metal", "shape": "cylinder"}, {"x": 20.492520224990916, "y": 81.82936466461797, "color": "green", "material": "rubber", "shape": "sphere"}, {"x": 20.460335658344402, "y": 94.89214261606595, "color": "cyan", "material": "metal", "shape": "cube"}, {"x": 12.64283259964173, "y": 77.9039506377371, "color": "red", "material": "rubber", "shape": "cylinder"}, {"x": 37.03530665389826, "y": 115.3125521005562, "color": "blue", "material": "rubber", "shape": "sphere"}, {"x": 30.000005053694036, "y": 35.000045787259836, "color": "yellow", "material": "rubber", "shape": "sphere"}]}, {"frame_index": 115, "objects": [{"x": 24.753901502695854, "y": 90.56473015435184, "color": "gray", "material": "metal", "shape": "cylinder"}, {"x": 19.412015629908208, "y": 80.9599272341575, "color": "green", "material": "rubber", "shape": "sphere"}, {"x": 21.03457073569796, "y": 93.5778646849711, "color": "cyan", "material": "metal", "shape": "cube"}, {"x": 13.776598299344712, "y": 78.13177405270942, "color": "red", "material": "rubber", "shape": "cylinder"}, {"x": 37.0453844069222, "y": 115.31238293398354, "color": "blue", "material": "rubber", "shape": "sphere"}, {"x": 30.000005053694036, "y": 35.000045787259836, "color": "yellow", "material": "rubber", "shape": "sphere"}]}, {"frame_index": 120, "objects": [{"x": 25.424606759204384, "y": 88.92283329789255, "color": "gray", "material": "metal", "shape": "cylinder"}, {"x": 18.37491900467665, "y": 80.12541757342358, "color": "green", "material": "rubber", "shape": "sphere"}, {"x": 20.952358165440906, "y": 92.96714528106246, "color": "cyan", "material": "metal", "shape": "cube"}, {"x": 14.901931773321785, "y": 78.35790264385477, "color": "red", "material": "rubber", "shape": "cylinder"}, {"x": 37.05546464471992, "y": 115.31221372570111, "color": "blue", "material": "rubber", "shape": "sphere"}, {"x": 30.000005053694036, "y": 35.000045787259836, "color": "yellow", "material": "rubber", "shape": "sphere"}]}, {"frame_index": 125, "objects": [{"x": 26.06190520738111, "y": 87.36272062663073, "color": "gray", "material": "metal", "shape": "cylinder"}, {"x": 18.15311952098513, "y": 79.71741168211175, "color": "green", "material": "rubber", "shape": "sphere"}, {"x": 20.88965542600342, "y": 92.50133809666794, "color": "cyan", "material": "metal", "shape": "cube"}, {"x": 15.188615412509488, "y": 78.19685471240386, "color": "red", "material": "rubber", "shape": "cylinder"}, {"x": 37.065547368210495, "y": 115.31204447569345, "color": "blue", "material": "rubber", "shape": "sphere"}, {"x": 30.000005053694036, "y": 35.000045787259836, "color": "yellow", "material": "rubber", "shape": "sphere"}]}], "collisions": [{"frame": 69, "objects": [{"color": "gray", "material": "metal", "shape": "cylinder"}, {"color": "green", "material": "rubber", "shape": "sphere"}]}, {"frame": 114, "objects": [{"color": "gray", "material": "metal", "shape": "cylinder"}, {"color": "cyan", "material": "metal", "shape": "cube"}]}, {"frame": 121, "objects": [{"color": "green", "material": "rubber", "shape": "sphere"}, {"color": "red", "material": "rubber", "shape": "cylinder"}]}]}], "step_88": {"x": [[-1.174818754196167, 0.8173741102218628], [-1.4034059047698975, 0.34402570128440857], [-2.771620750427246, 1.2780765295028687], [-3.959559202194214, 0.0995313748717308], [-0.49619001150131226, 1.3095899820327759], [-1.0752999782562256, -1.4217100143432617]], "v": [[-1.0103451013565063, 0.018126534298062325], [-0.867141604423523, -0.49352526664733887], [1.2272132635116577, -0.7706993818283081], [1.4789222478866577, 0.038305044174194336], [-1.256052200915292e-06, 1.8772369003272615e-05], [0.0, 0.0]], "angle": [0.0, 0.0, 1.1924039125442505, 0.0, 0.0, 0.0], "mass": [0.7355480790138245, 0.3457685112953186, 1.7228502035140991, 0.9985002875328064, 1.0, 1.0], "restitution": [0.32890844345092773, -0.1517135202884674, 0.6806151270866394, 0.6000297665596008, 0.6000000238418579, 0.6000000238418579]}, "step_108": {"x": [[-1.6953808069229126, 0.8267133831977844], [-1.8906275033950806, 0.06672818213701248], [-2.1266603469848633, 0.8730374574661255], [-3.1817188262939453, 0.1196778267621994], [-0.49619001150131226, 1.3095899820327759], [-1.0752999782562256, -1.4217100143432617]], "v": [[-0.8136720657348633, 0.014598018489778042], [-0.8384546041488647, -0.47719815373420715], [1.0331064462661743, -0.6487944722175598], [1.2471281290054321, 0.032301049679517746], [-1.256052200915292e-06, 1.8772369003272615e-05], [0.0, 0.0]], "angle": [0.0, 0.0, 1.1924039125442505, 0.0, 0.0, 0.0], "mass": [0.7355480790138245, 0.3457685112953186, 1.7228502035140991, 0.9985002875328064, 1.0, 1.0], "restitution": [0.32890844345092773, -0.1517135202884674, 0.6806151270866394, 0.6000297665596008, 0.6000000238418579, 0.6000000238418579]}}